dacon/__init__.py
dacon/datasets/__init__.py
dacon/datasets/_base.py
dacon/datasets/cpt_list.py
dacon/datasets/download_from_gdrive.py
dacon/datasets/data/__init__.py
dacon/datasets/data/235862/__init__.py
dacon/datasets/data/235862/sample_submission.csv
dacon/datasets/data/235862/test.csv
dacon/datasets/data/235862/train.csv
dacon/datasets/data/235876/__init__.py
dacon/datasets/data/235876/sample_submission.csv
dacon/datasets/data/235876/test.csv
dacon/datasets/data/235876/train.csv
dacon-0.1.5.dist-info/LICENSE
dacon-0.1.5.dist-info/METADATA
dacon-0.1.5.dist-info/WHEEL
dacon-0.1.5.dist-info/top_level.txt
dacon-0.1.5.dist-info/RECORD
